mixpanel_api/__init__.py
mixpanel_api/dataset_load_example.py
mixpanel_api/datasets_examples.py
mixpanel_api/mixpanel_api_example.py
mixpanel_api/paginator.py
mixpanel_api-1.6.4.dist-info/METADATA
mixpanel_api-1.6.4.dist-info/WHEEL
mixpanel_api-1.6.4.dist-info/top_level.txt
mixpanel_api-1.6.4.dist-info/RECORD
