Metadata-Version: 2.1
Name: mixpanel-api
Version: 1.6.4
Summary: Utilities-only module for exporting and importing data into Mixpanel. NOT for server-side app tracking.
Home-page: http://www.mixpanel.com
Author: Jared McFarland
Author-email: jared@mixpanel.com
License: UNKNOWN
Platform: UNKNOWN
